mafe/__init__.py
mafe/mafe.py
mafe/process/__init__.py
mafe/process/calculate_distances.py
mafe/process/cluster.py
mafe/process/normalize.py
mafe/process/pca.py
mafe/process/scatter_plot.py
mafe/scan/__init__.py
mafe/scan/scanner.py
mafe/scan/track_data.py
mafe/scan/track_data_duck.py
mafe/scan/track_data_storage.py
mafe/scan/track_metadata.py
mafe/scan/types.py
mafe-0.3.1.dist-info/entry_points.txt
mafe-0.3.1.dist-info/LICENSE
mafe-0.3.1.dist-info/WHEEL
mafe-0.3.1.dist-info/METADATA
mafe-0.3.1.dist-info/RECORD
